[
  {
    "name": "半加算回路",
    "nodes": [
      {
        "x": 390,
        "y": 1099,
        "type": "normal"
      },
      {
        "x": 518.65,
        "y": 1095.03,
        "type": "xor"
      },
      {
        "x": 519.883,
        "y": 1239.75,
        "type": "and"
      },
      {
        "x": 385,
        "y": 1257,
        "type": "normal"
      }
    ],
    "connections": [
      {
        "from": 3,
        "to": 2,
        "fromPin": "OUT",
        "toPin": "A"
      },
      {
        "from": 0,
        "to": 2,
        "fromPin": "OUT",
        "toPin": "B"
      },
      {
        "from": 3,
        "to": 1,
        "fromPin": "OUT",
        "toPin": "A"
      },
      {
        "from": 0,
        "to": 1,
        "fromPin": "OUT",
        "toPin": "B"
      }
    ]
  },
  {
    "name": "全加算回路",
    "nodes": [
      {
        "x": 291.922,
        "y": 1273.83,
        "type": "positive"
      },
      {
        "x": 422.598,
        "y": 1314.06,
        "type": "normal"
      },
      {
        "x": 292.14,
        "y": 1378.85,
        "type": "positive"
      },
      {
        "x": 508.58,
        "y": 1401.6,
        "type": "and"
      },
      {
        "x": 507.347,
        "y": 1312.76,
        "type": "xor"
      },
      {
        "x": 418.951,
        "y": 1421.51,
        "type": "normal"
      },
      {
        "x": 627.47,
        "y": 1336.48,
        "type": "normal"
      },
      {
        "x": 736.08,
        "y": 1518.51,
        "type": "and"
      },
      {
        "x": 613.837,
        "y": 1538.07,
        "type": "normal"
      },
      {
        "x": 291.737,
        "y": 1493.73,
        "type": "positive"
      },
      {
        "x": 742.819,
        "y": 1335.16,
        "type": "xor"
      },
      {
        "x": 859.889,
        "y": 1419.28,
        "type": "or"
      },
      {
        "x": 877.103,
        "y": 1357.26,
        "type": "normal"
      },
      {
        "x": 989.087,
        "y": 1346.13,
        "type": "negative"
      },
      {
        "x": 985.247,
        "y": 1425.52,
        "type": "negative"
      }
    ],
    "connections": [
      {
        "from": 0,
        "to": 1,
        "fromPin": "OUT",
        "toPin": "IN"
      },
      {
        "from": 2,
        "to": 5,
        "fromPin": "OUT",
        "toPin": "IN"
      },
      {
        "from": 5,
        "to": 3,
        "fromPin": "OUT",
        "toPin": "A"
      },
      {
        "from": 1,
        "to": 3,
        "fromPin": "OUT",
        "toPin": "B"
      },
      {
        "from": 5,
        "to": 4,
        "fromPin": "OUT",
        "toPin": "A"
      },
      {
        "from": 1,
        "to": 4,
        "fromPin": "OUT",
        "toPin": "B"
      },
      {
        "from": 8,
        "to": 7,
        "fromPin": "OUT",
        "toPin": "A"
      },
      {
        "from": 6,
        "to": 7,
        "fromPin": "OUT",
        "toPin": "B"
      },
      {
        "from": 8,
        "to": 10,
        "fromPin": "OUT",
        "toPin": "A"
      },
      {
        "from": 6,
        "to": 10,
        "fromPin": "OUT",
        "toPin": "B"
      },
      {
        "from": 9,
        "to": 8,
        "fromPin": "OUT",
        "toPin": "IN"
      },
      {
        "from": 4,
        "to": 6,
        "fromPin": "OUT",
        "toPin": "IN"
      },
      {
        "from": 3,
        "to": 11,
        "fromPin": "OUT",
        "toPin": "B"
      },
      {
        "from": 7,
        "to": 11,
        "fromPin": "OUT",
        "toPin": "A"
      },
      {
        "from": 11,
        "to": 14,
        "fromPin": "OUT",
        "toPin": "IN"
      },
      {
        "from": 10,
        "to": 12,
        "fromPin": "OUT",
        "toPin": "IN"
      },
      {
        "from": 12,
        "to": 13,
        "fromPin": "OUT",
        "toPin": "IN"
      }
    ]
  },
  {
    "name": "三桁",
    "nodes": [
      {
        "x": 281.274,
        "y": 1392.29,
        "type": "positive"
      },
      {
        "x": 281.492,
        "y": 1497.31,
        "type": "positive"
      },
      {
        "x": 281.089,
        "y": 1612.19,
        "type": "positive"
      },
      {
        "x": 411.95,
        "y": 1432.52,
        "type": "normal"
      },
      {
        "x": 408.303,
        "y": 1539.97,
        "type": "normal"
      },
      {
        "x": 163.69,
        "y": 1711.09,
        "type": "normal"
      },
      {
        "x": 282.586,
        "y": 1728.17,
        "type": "positive"
      },
      {
        "x": 413.262,
        "y": 1768.4,
        "type": "normal"
      },
      {
        "x": 497.932,
        "y": 1520.06,
        "type": "and"
      },
      {
        "x": 496.699,
        "y": 1431.22,
        "type": "xor"
      },
      {
        "x": 282.804,
        "y": 1833.19,
        "type": "positive"
      },
      {
        "x": 499.244,
        "y": 1855.94,
        "type": "and"
      },
      {
        "x": 498.011,
        "y": 1767.1,
        "type": "xor"
      },
      {
        "x": 409.615,
        "y": 1875.85,
        "type": "normal"
      },
      {
        "x": 616.822,
        "y": 1454.94,
        "type": "normal"
      },
      {
        "x": 603.189,
        "y": 1656.53,
        "type": "normal"
      },
      {
        "x": 618.134,
        "y": 1790.82,
        "type": "normal"
      },
      {
        "x": 604.501,
        "y": 1992.41,
        "type": "normal"
      },
      {
        "x": 204.95,
        "y": 1975.97,
        "type": "normal"
      },
      {
        "x": 732.171,
        "y": 1453.62,
        "type": "xor"
      },
      {
        "x": 725.432,
        "y": 1636.97,
        "type": "and"
      },
      {
        "x": 726.745,
        "y": 1972.85,
        "type": "and"
      },
      {
        "x": 733.485,
        "y": 1789.5,
        "type": "xor"
      },
      {
        "x": 849.241,
        "y": 1537.74,
        "type": "or"
      },
      {
        "x": 850.555,
        "y": 1873.62,
        "type": "or"
      },
      {
        "x": 866.455,
        "y": 1475.72,
        "type": "normal"
      },
      {
        "x": 867.765,
        "y": 1811.6,
        "type": "normal"
      },
      {
        "x": 975.914,
        "y": 1879.86,
        "type": "negative"
      },
      {
        "x": 967.264,
        "y": 1463.19,
        "type": "negative"
      },
      {
        "x": 979.754,
        "y": 1800.47,
        "type": "negative"
      },
      {
        "x": 1006.2,
        "y": 1684.48,
        "type": "normal"
      }
    ],
    "connections": [
      {
        "from": 0,
        "to": 3,
        "fromPin": "OUT",
        "toPin": "IN"
      },
      {
        "from": 1,
        "to": 4,
        "fromPin": "OUT",
        "toPin": "IN"
      },
      {
        "from": 4,
        "to": 8,
        "fromPin": "OUT",
        "toPin": "A"
      },
      {
        "from": 3,
        "to": 8,
        "fromPin": "OUT",
        "toPin": "B"
      },
      {
        "from": 4,
        "to": 9,
        "fromPin": "OUT",
        "toPin": "A"
      },
      {
        "from": 3,
        "to": 9,
        "fromPin": "OUT",
        "toPin": "B"
      },
      {
        "from": 15,
        "to": 20,
        "fromPin": "OUT",
        "toPin": "A"
      },
      {
        "from": 14,
        "to": 20,
        "fromPin": "OUT",
        "toPin": "B"
      },
      {
        "from": 15,
        "to": 19,
        "fromPin": "OUT",
        "toPin": "A"
      },
      {
        "from": 14,
        "to": 19,
        "fromPin": "OUT",
        "toPin": "B"
      },
      {
        "from": 2,
        "to": 15,
        "fromPin": "OUT",
        "toPin": "IN"
      },
      {
        "from": 9,
        "to": 14,
        "fromPin": "OUT",
        "toPin": "IN"
      },
      {
        "from": 8,
        "to": 23,
        "fromPin": "OUT",
        "toPin": "B"
      },
      {
        "from": 20,
        "to": 23,
        "fromPin": "OUT",
        "toPin": "A"
      },
      {
        "from": 19,
        "to": 25,
        "fromPin": "OUT",
        "toPin": "IN"
      },
      {
        "from": 6,
        "to": 7,
        "fromPin": "OUT",
        "toPin": "IN"
      },
      {
        "from": 10,
        "to": 13,
        "fromPin": "OUT",
        "toPin": "IN"
      },
      {
        "from": 13,
        "to": 11,
        "fromPin": "OUT",
        "toPin": "A"
      },
      {
        "from": 7,
        "to": 11,
        "fromPin": "OUT",
        "toPin": "B"
      },
      {
        "from": 13,
        "to": 12,
        "fromPin": "OUT",
        "toPin": "A"
      },
      {
        "from": 7,
        "to": 12,
        "fromPin": "OUT",
        "toPin": "B"
      },
      {
        "from": 17,
        "to": 21,
        "fromPin": "OUT",
        "toPin": "A"
      },
      {
        "from": 16,
        "to": 21,
        "fromPin": "OUT",
        "toPin": "B"
      },
      {
        "from": 17,
        "to": 22,
        "fromPin": "OUT",
        "toPin": "A"
      },
      {
        "from": 16,
        "to": 22,
        "fromPin": "OUT",
        "toPin": "B"
      },
      {
        "from": 12,
        "to": 16,
        "fromPin": "OUT",
        "toPin": "IN"
      },
      {
        "from": 11,
        "to": 24,
        "fromPin": "OUT",
        "toPin": "B"
      },
      {
        "from": 21,
        "to": 24,
        "fromPin": "OUT",
        "toPin": "A"
      },
      {
        "from": 24,
        "to": 27,
        "fromPin": "OUT",
        "toPin": "IN"
      },
      {
        "from": 22,
        "to": 26,
        "fromPin": "OUT",
        "toPin": "IN"
      },
      {
        "from": 26,
        "to": 29,
        "fromPin": "OUT",
        "toPin": "IN"
      },
      {
        "from": 18,
        "to": 17,
        "fromPin": "OUT",
        "toPin": "IN"
      },
      {
        "from": 5,
        "to": 18,
        "fromPin": "OUT",
        "toPin": "IN"
      },
      {
        "from": 25,
        "to": 28,
        "fromPin": "OUT",
        "toPin": "IN"
      },
      {
        "from": 23,
        "to": 30,
        "fromPin": "OUT",
        "toPin": "IN"
      },
      {
        "from": 30,
        "to": 5,
        "fromPin": "OUT",
        "toPin": "IN"
      }
    ]
  },
  {
    "name": "5ビット入力装置",
    "nodes": [
      {
        "x": -264.343,
        "y": 841.787,
        "type": "positive"
      },
      {
        "x": -264.125,
        "y": 946.807,
        "type": "positive"
      },
      {
        "x": -133.667,
        "y": 882.017,
        "type": "normal"
      },
      {
        "x": -137.314,
        "y": 989.467,
        "type": "normal"
      },
      {
        "x": -263.031,
        "y": 1177.66,
        "type": "positive"
      },
      {
        "x": -381.927,
        "y": 1160.59,
        "type": "normal"
      },
      {
        "x": -47.6854,
        "y": 969.557,
        "type": "and"
      },
      {
        "x": -48.9184,
        "y": 880.717,
        "type": "xor"
      },
      {
        "x": 57.5716,
        "y": 1106.03,
        "type": "normal"
      },
      {
        "x": -132.355,
        "y": 1217.89,
        "type": "normal"
      },
      {
        "x": -262.813,
        "y": 1282.68,
        "type": "positive"
      },
      {
        "x": -46.3734,
        "y": 1305.43,
        "type": "and"
      },
      {
        "x": -47.6064,
        "y": 1216.59,
        "type": "xor"
      },
      {
        "x": -136.002,
        "y": 1325.34,
        "type": "normal"
      },
      {
        "x": 71.2046,
        "y": 904.437,
        "type": "normal"
      },
      {
        "x": 72.5166,
        "y": 1240.31,
        "type": "normal"
      },
      {
        "x": -340.667,
        "y": 1425.46,
        "type": "normal"
      },
      {
        "x": 58.8836,
        "y": 1441.9,
        "type": "normal"
      },
      {
        "x": -267.419,
        "y": 1491.98,
        "type": "positive"
      },
      {
        "x": -376.893,
        "y": 1467.83,
        "type": "normal"
      },
      {
        "x": 186.55,
        "y": 903.117,
        "type": "xor"
      },
      {
        "x": 179.81,
        "y": 1086.47,
        "type": "and"
      },
      {
        "x": 181.13,
        "y": 1422.34,
        "type": "and"
      },
      {
        "x": 187.87,
        "y": 1238.99,
        "type": "xor"
      },
      {
        "x": -136.743,
        "y": 1532.21,
        "type": "normal"
      },
      {
        "x": -51.9944,
        "y": 1530.91,
        "type": "xor"
      },
      {
        "x": 68.1286,
        "y": 1554.63,
        "type": "normal"
      },
      {
        "x": 183.48,
        "y": 1553.31,
        "type": "xor"
      },
      {
        "x": -267.201,
        "y": 1597,
        "type": "positive"
      },
      {
        "x": -50.7614,
        "y": 1619.75,
        "type": "and"
      },
      {
        "x": -140.39,
        "y": 1639.66,
        "type": "normal"
      },
      {
        "x": 303.62,
        "y": 987.237,
        "type": "or"
      },
      {
        "x": 304.94,
        "y": 1323.11,
        "type": "or"
      },
      {
        "x": 300.55,
        "y": 1637.43,
        "type": "or"
      },
      {
        "x": 320.84,
        "y": 925.217,
        "type": "normal"
      },
      {
        "x": 322.15,
        "y": 1261.09,
        "type": "normal"
      },
      {
        "x": 178.35,
        "y": 1726.97,
        "type": "and"
      },
      {
        "x": 317.76,
        "y": 1575.41,
        "type": "normal"
      },
      {
        "x": -333.475,
        "y": 1736.88,
        "type": "normal"
      },
      {
        "x": 70.3726,
        "y": 1749.65,
        "type": "normal"
      },
      {
        "x": -395.609,
        "y": 1792.33,
        "type": "normal"
      },
      {
        "x": -263.533,
        "y": 1823.88,
        "type": "positive"
      },
      {
        "x": -132.863,
        "y": 1864.11,
        "type": "normal"
      },
      {
        "x": -48.1134,
        "y": 1862.81,
        "type": "xor"
      },
      {
        "x": 421.65,
        "y": 912.687,
        "type": "negative"
      },
      {
        "x": 429.74,
        "y": 1564.28,
        "type": "negative"
      },
      {
        "x": 72.0166,
        "y": 1886.53,
        "type": "normal"
      },
      {
        "x": 187.37,
        "y": 1885.21,
        "type": "xor"
      },
      {
        "x": 321.65,
        "y": 1907.31,
        "type": "normal"
      },
      {
        "x": 422.46,
        "y": 1894.78,
        "type": "negative"
      },
      {
        "x": 428.73,
        "y": 1663.72,
        "type": "normal"
      },
      {
        "x": 434.14,
        "y": 1249.96,
        "type": "negative"
      },
      {
        "x": 441.28,
        "y": 1346.01,
        "type": "normal"
      },
      {
        "x": -263.314,
        "y": 1928.89,
        "type": "positive"
      },
      {
        "x": -46.8734,
        "y": 1951.65,
        "type": "and"
      },
      {
        "x": 460.58,
        "y": 1133.98,
        "type": "normal"
      },
      {
        "x": 464.01,
        "y": 1489.64,
        "type": "normal"
      },
      {
        "x": -136.503,
        "y": 1971.56,
        "type": "normal"
      },
      {
        "x": 304.44,
        "y": 1969.33,
        "type": "or"
      },
      {
        "x": 459.9,
        "y": 1788.44,
        "type": "normal"
      },
      {
        "x": 180.63,
        "y": 2068.56,
        "type": "and"
      },
      {
        "x": -348.832,
        "y": 2069.05,
        "type": "normal"
      },
      {
        "x": 58.3766,
        "y": 2088.12,
        "type": "normal"
      },
      {
        "x": 461.39,
        "y": 2116.07,
        "type": "normal"
      },
      {
        "x": -381.118,
        "y": 2142.68,
        "type": "normal"
      },
      {
        "x": -262.223,
        "y": 2159.76,
        "type": "positive"
      },
      {
        "x": -131.543,
        "y": 2199.99,
        "type": "normal"
      },
      {
        "x": -46.7934,
        "y": 2198.69,
        "type": "xor"
      },
      {
        "x": 73.3266,
        "y": 2222.41,
        "type": "normal"
      },
      {
        "x": 188.68,
        "y": 2221.09,
        "type": "xor"
      },
      {
        "x": 434.95,
        "y": 2232.06,
        "type": "negative"
      },
      {
        "x": 322.96,
        "y": 2243.19,
        "type": "normal"
      },
      {
        "x": -262.003,
        "y": 2264.78,
        "type": "positive"
      },
      {
        "x": -45.5634,
        "y": 2287.53,
        "type": "and"
      },
      {
        "x": -135.193,
        "y": 2307.44,
        "type": "normal"
      },
      {
        "x": 305.75,
        "y": 2305.21,
        "type": "or"
      },
      {
        "x": 431.11,
        "y": 2311.45,
        "type": "negative"
      },
      {
        "x": -339.863,
        "y": 2407.56,
        "type": "normal"
      },
      {
        "x": 181.94,
        "y": 2404.44,
        "type": "and"
      },
      {
        "x": 59.6966,
        "y": 2424,
        "type": "normal"
      }
    ],
    "connections": [
      {
        "from": 0,
        "to": 2,
        "fromPin": "OUT",
        "toPin": "IN"
      },
      {
        "from": 1,
        "to": 3,
        "fromPin": "OUT",
        "toPin": "IN"
      },
      {
        "from": 3,
        "to": 6,
        "fromPin": "OUT",
        "toPin": "A"
      },
      {
        "from": 2,
        "to": 6,
        "fromPin": "OUT",
        "toPin": "B"
      },
      {
        "from": 3,
        "to": 7,
        "fromPin": "OUT",
        "toPin": "A"
      },
      {
        "from": 2,
        "to": 7,
        "fromPin": "OUT",
        "toPin": "B"
      },
      {
        "from": 8,
        "to": 21,
        "fromPin": "OUT",
        "toPin": "A"
      },
      {
        "from": 14,
        "to": 21,
        "fromPin": "OUT",
        "toPin": "B"
      },
      {
        "from": 8,
        "to": 20,
        "fromPin": "OUT",
        "toPin": "A"
      },
      {
        "from": 14,
        "to": 20,
        "fromPin": "OUT",
        "toPin": "B"
      },
      {
        "from": 7,
        "to": 14,
        "fromPin": "OUT",
        "toPin": "IN"
      },
      {
        "from": 6,
        "to": 31,
        "fromPin": "OUT",
        "toPin": "B"
      },
      {
        "from": 21,
        "to": 31,
        "fromPin": "OUT",
        "toPin": "A"
      },
      {
        "from": 20,
        "to": 34,
        "fromPin": "OUT",
        "toPin": "IN"
      },
      {
        "from": 4,
        "to": 9,
        "fromPin": "OUT",
        "toPin": "IN"
      },
      {
        "from": 10,
        "to": 13,
        "fromPin": "OUT",
        "toPin": "IN"
      },
      {
        "from": 13,
        "to": 11,
        "fromPin": "OUT",
        "toPin": "A"
      },
      {
        "from": 9,
        "to": 11,
        "fromPin": "OUT",
        "toPin": "B"
      },
      {
        "from": 13,
        "to": 12,
        "fromPin": "OUT",
        "toPin": "A"
      },
      {
        "from": 9,
        "to": 12,
        "fromPin": "OUT",
        "toPin": "B"
      },
      {
        "from": 17,
        "to": 22,
        "fromPin": "OUT",
        "toPin": "A"
      },
      {
        "from": 15,
        "to": 22,
        "fromPin": "OUT",
        "toPin": "B"
      },
      {
        "from": 17,
        "to": 23,
        "fromPin": "OUT",
        "toPin": "A"
      },
      {
        "from": 15,
        "to": 23,
        "fromPin": "OUT",
        "toPin": "B"
      },
      {
        "from": 12,
        "to": 15,
        "fromPin": "OUT",
        "toPin": "IN"
      },
      {
        "from": 11,
        "to": 32,
        "fromPin": "OUT",
        "toPin": "B"
      },
      {
        "from": 22,
        "to": 32,
        "fromPin": "OUT",
        "toPin": "A"
      },
      {
        "from": 23,
        "to": 35,
        "fromPin": "OUT",
        "toPin": "IN"
      },
      {
        "from": 35,
        "to": 51,
        "fromPin": "OUT",
        "toPin": "IN"
      },
      {
        "from": 16,
        "to": 17,
        "fromPin": "OUT",
        "toPin": "IN"
      },
      {
        "from": 5,
        "to": 16,
        "fromPin": "OUT",
        "toPin": "IN"
      },
      {
        "from": 34,
        "to": 44,
        "fromPin": "OUT",
        "toPin": "IN"
      },
      {
        "from": 31,
        "to": 55,
        "fromPin": "OUT",
        "toPin": "IN"
      },
      {
        "from": 55,
        "to": 5,
        "fromPin": "OUT",
        "toPin": "IN"
      },
      {
        "from": 18,
        "to": 24,
        "fromPin": "OUT",
        "toPin": "IN"
      },
      {
        "from": 28,
        "to": 30,
        "fromPin": "OUT",
        "toPin": "IN"
      },
      {
        "from": 30,
        "to": 29,
        "fromPin": "OUT",
        "toPin": "A"
      },
      {
        "from": 24,
        "to": 29,
        "fromPin": "OUT",
        "toPin": "B"
      },
      {
        "from": 30,
        "to": 25,
        "fromPin": "OUT",
        "toPin": "A"
      },
      {
        "from": 24,
        "to": 25,
        "fromPin": "OUT",
        "toPin": "B"
      },
      {
        "from": 26,
        "to": 36,
        "fromPin": "OUT",
        "toPin": "B"
      },
      {
        "from": 26,
        "to": 27,
        "fromPin": "OUT",
        "toPin": "B"
      },
      {
        "from": 25,
        "to": 26,
        "fromPin": "OUT",
        "toPin": "IN"
      },
      {
        "from": 29,
        "to": 33,
        "fromPin": "OUT",
        "toPin": "B"
      },
      {
        "from": 36,
        "to": 33,
        "fromPin": "OUT",
        "toPin": "A"
      },
      {
        "from": 27,
        "to": 37,
        "fromPin": "OUT",
        "toPin": "IN"
      },
      {
        "from": 37,
        "to": 45,
        "fromPin": "OUT",
        "toPin": "IN"
      },
      {
        "from": 32,
        "to": 52,
        "fromPin": "OUT",
        "toPin": "IN"
      },
      {
        "from": 39,
        "to": 36,
        "fromPin": "OUT",
        "toPin": "A"
      },
      {
        "from": 39,
        "to": 27,
        "fromPin": "OUT",
        "toPin": "A"
      },
      {
        "from": 38,
        "to": 39,
        "fromPin": "OUT",
        "toPin": "IN"
      },
      {
        "from": 19,
        "to": 38,
        "fromPin": "OUT",
        "toPin": "IN"
      },
      {
        "from": 56,
        "to": 19,
        "fromPin": "OUT",
        "toPin": "IN"
      },
      {
        "from": 52,
        "to": 56,
        "fromPin": "OUT",
        "toPin": "IN"
      },
      {
        "from": 41,
        "to": 42,
        "fromPin": "OUT",
        "toPin": "IN"
      },
      {
        "from": 53,
        "to": 57,
        "fromPin": "OUT",
        "toPin": "IN"
      },
      {
        "from": 57,
        "to": 54,
        "fromPin": "OUT",
        "toPin": "A"
      },
      {
        "from": 42,
        "to": 54,
        "fromPin": "OUT",
        "toPin": "B"
      },
      {
        "from": 57,
        "to": 43,
        "fromPin": "OUT",
        "toPin": "A"
      },
      {
        "from": 42,
        "to": 43,
        "fromPin": "OUT",
        "toPin": "B"
      },
      {
        "from": 62,
        "to": 60,
        "fromPin": "OUT",
        "toPin": "A"
      },
      {
        "from": 46,
        "to": 60,
        "fromPin": "OUT",
        "toPin": "B"
      },
      {
        "from": 62,
        "to": 47,
        "fromPin": "OUT",
        "toPin": "A"
      },
      {
        "from": 46,
        "to": 47,
        "fromPin": "OUT",
        "toPin": "B"
      },
      {
        "from": 43,
        "to": 46,
        "fromPin": "OUT",
        "toPin": "IN"
      },
      {
        "from": 54,
        "to": 58,
        "fromPin": "OUT",
        "toPin": "B"
      },
      {
        "from": 60,
        "to": 58,
        "fromPin": "OUT",
        "toPin": "A"
      },
      {
        "from": 47,
        "to": 48,
        "fromPin": "OUT",
        "toPin": "IN"
      },
      {
        "from": 65,
        "to": 66,
        "fromPin": "OUT",
        "toPin": "IN"
      },
      {
        "from": 72,
        "to": 74,
        "fromPin": "OUT",
        "toPin": "IN"
      },
      {
        "from": 74,
        "to": 73,
        "fromPin": "OUT",
        "toPin": "A"
      },
      {
        "from": 66,
        "to": 73,
        "fromPin": "OUT",
        "toPin": "B"
      },
      {
        "from": 74,
        "to": 67,
        "fromPin": "OUT",
        "toPin": "A"
      },
      {
        "from": 66,
        "to": 67,
        "fromPin": "OUT",
        "toPin": "B"
      },
      {
        "from": 79,
        "to": 78,
        "fromPin": "OUT",
        "toPin": "A"
      },
      {
        "from": 68,
        "to": 78,
        "fromPin": "OUT",
        "toPin": "B"
      },
      {
        "from": 79,
        "to": 69,
        "fromPin": "OUT",
        "toPin": "A"
      },
      {
        "from": 68,
        "to": 69,
        "fromPin": "OUT",
        "toPin": "B"
      },
      {
        "from": 67,
        "to": 68,
        "fromPin": "OUT",
        "toPin": "IN"
      },
      {
        "from": 73,
        "to": 75,
        "fromPin": "OUT",
        "toPin": "B"
      },
      {
        "from": 78,
        "to": 75,
        "fromPin": "OUT",
        "toPin": "A"
      },
      {
        "from": 75,
        "to": 76,
        "fromPin": "OUT",
        "toPin": "IN"
      },
      {
        "from": 69,
        "to": 71,
        "fromPin": "OUT",
        "toPin": "IN"
      },
      {
        "from": 71,
        "to": 70,
        "fromPin": "OUT",
        "toPin": "IN"
      },
      {
        "from": 77,
        "to": 79,
        "fromPin": "OUT",
        "toPin": "IN"
      },
      {
        "from": 64,
        "to": 77,
        "fromPin": "OUT",
        "toPin": "IN"
      },
      {
        "from": 48,
        "to": 49,
        "fromPin": "OUT",
        "toPin": "IN"
      },
      {
        "from": 58,
        "to": 63,
        "fromPin": "OUT",
        "toPin": "IN"
      },
      {
        "from": 63,
        "to": 64,
        "fromPin": "OUT",
        "toPin": "IN"
      },
      {
        "from": 33,
        "to": 50,
        "fromPin": "OUT",
        "toPin": "IN"
      },
      {
        "from": 50,
        "to": 59,
        "fromPin": "OUT",
        "toPin": "IN"
      },
      {
        "from": 59,
        "to": 40,
        "fromPin": "OUT",
        "toPin": "IN"
      },
      {
        "from": 40,
        "to": 61,
        "fromPin": "OUT",
        "toPin": "IN"
      },
      {
        "from": 61,
        "to": 62,
        "fromPin": "OUT",
        "toPin": "IN"
      }
    ]
  },
  {
    "name": "セレクタ",
    "nodes": [
      {
        "x": 220.425,
        "y": 659.1,
        "type": "normal"
      },
      {
        "x": 297,
        "y": 685.5,
        "type": "not"
      },
      {
        "x": 403,
        "y": 666.5,
        "type": "and"
      },
      {
        "x": 221.525,
        "y": 750.4,
        "type": "normal"
      },
      {
        "x": 398,
        "y": 813.5,
        "type": "and"
      },
      {
        "x": 220.425,
        "y": 831.8,
        "type": "normal"
      },
      {
        "x": 502,
        "y": 739.5,
        "type": "or"
      },
      {
        "x": 606.525,
        "y": 755.9,
        "type": "normal"
      }
    ],
    "connections": [
      {
        "from": 2,
        "to": 6,
        "fromPin": "OUT",
        "toPin": "B"
      },
      {
        "from": 4,
        "to": 6,
        "fromPin": "OUT",
        "toPin": "A"
      },
      {
        "from": 1,
        "to": 2,
        "fromPin": "OUT",
        "toPin": "A"
      },
      {
        "from": 0,
        "to": 2,
        "fromPin": "OUT",
        "toPin": "B"
      },
      {
        "from": 3,
        "to": 1,
        "fromPin": "OUT",
        "toPin": "IN"
      },
      {
        "from": 3,
        "to": 4,
        "fromPin": "OUT",
        "toPin": "B"
      },
      {
        "from": 5,
        "to": 4,
        "fromPin": "OUT",
        "toPin": "A"
      },
      {
        "from": 6,
        "to": 7,
        "fromPin": "OUT",
        "toPin": "IN"
      }
    ]
  },
  {
    "name": "ADD_AND_4bit",
    "nodes": [
      {
        "x": 4253.44,
        "y": 4665.26,
        "type": "normal"
      },
      {
        "x": 4249.79,
        "y": 4772.71,
        "type": "normal"
      },
      {
        "x": 4249.05,
        "y": 4979.58,
        "type": "normal"
      },
      {
        "x": 4245.4,
        "y": 5087.03,
        "type": "normal"
      },
      {
        "x": 4252.93,
        "y": 5311.48,
        "type": "normal"
      },
      {
        "x": 4249.29,
        "y": 5418.93,
        "type": "normal"
      },
      {
        "x": 3839.26,
        "y": 5590.34,
        "type": "normal"
      },
      {
        "x": 3840.25,
        "y": 5561.61,
        "type": "normal"
      },
      {
        "x": 4254.25,
        "y": 5647.36,
        "type": "normal"
      },
      {
        "x": 3843.26,
        "y": 5645.23,
        "type": "normal"
      },
      {
        "x": 3841.23,
        "y": 5617.65,
        "type": "normal"
      },
      {
        "x": 4339.42,
        "y": 4752.8,
        "type": "and"
      },
      {
        "x": 4338.19,
        "y": 4663.96,
        "type": "xor"
      },
      {
        "x": 4458.31,
        "y": 4687.68,
        "type": "normal"
      },
      {
        "x": 4444.68,
        "y": 4889.27,
        "type": "normal"
      },
      {
        "x": 4333.8,
        "y": 4978.28,
        "type": "xor"
      },
      {
        "x": 4453.92,
        "y": 5002,
        "type": "normal"
      },
      {
        "x": 4335.03,
        "y": 5067.12,
        "type": "and"
      },
      {
        "x": 4456.16,
        "y": 5197.02,
        "type": "normal"
      },
      {
        "x": 4337.68,
        "y": 5310.18,
        "type": "xor"
      },
      {
        "x": 4457.81,
        "y": 5333.9,
        "type": "normal"
      },
      {
        "x": 4338.92,
        "y": 5399.02,
        "type": "and"
      },
      {
        "x": 4444.17,
        "y": 5535.49,
        "type": "normal"
      },
      {
        "x": 4339,
        "y": 5646.06,
        "type": "xor"
      },
      {
        "x": 4459.12,
        "y": 5669.78,
        "type": "normal"
      },
      {
        "x": 4340.23,
        "y": 5734.9,
        "type": "and"
      },
      {
        "x": 3841.25,
        "y": 5758.14,
        "type": "normal"
      },
      {
        "x": 3840.96,
        "y": 5730.41,
        "type": "normal"
      },
      {
        "x": 4249.52,
        "y": 5755.15,
        "type": "normal"
      },
      {
        "x": 3839.96,
        "y": 5787.73,
        "type": "normal"
      },
      {
        "x": 3841.81,
        "y": 5817.01,
        "type": "normal"
      },
      {
        "x": 4566.92,
        "y": 4869.71,
        "type": "and"
      },
      {
        "x": 4573.66,
        "y": 4686.36,
        "type": "xor"
      },
      {
        "x": 4569.27,
        "y": 5000.68,
        "type": "xor"
      },
      {
        "x": 4564.14,
        "y": 5174.34,
        "type": "and"
      },
      {
        "x": 4573.16,
        "y": 5332.58,
        "type": "xor"
      },
      {
        "x": 4684.05,
        "y": 4773.15,
        "type": "or"
      },
      {
        "x": 4678.34,
        "y": 5094.8,
        "type": "or"
      },
      {
        "x": 4690.23,
        "y": 5416.7,
        "type": "or"
      },
      {
        "x": 4566.42,
        "y": 5515.93,
        "type": "and"
      },
      {
        "x": 4707.16,
        "y": 5764.34,
        "type": "normal"
      },
      {
        "x": 4579.78,
        "y": 5671.11,
        "type": "xor"
      },
      {
        "x": 4691.54,
        "y": 5752.58,
        "type": "or"
      },
      {
        "x": 4567.73,
        "y": 5851.81,
        "type": "and"
      },
      {
        "x": 4445.49,
        "y": 5871.37,
        "type": "normal"
      },
      {
        "x": 4903.76,
        "y": 5026.32,
        "type": "normal"
      },
      {
        "x": 4911.18,
        "y": 5354.67,
        "type": "normal"
      },
      {
        "x": 4827.07,
        "y": 4793.38,
        "type": "normal"
      },
      {
        "x": 4833.8,
        "y": 5437.34,
        "type": "normal"
      },
      {
        "x": 4913.83,
        "y": 5690.89,
        "type": "normal"
      },
      {
        "x": 4841.6,
        "y": 5775.58,
        "type": "normal"
      },
      {
        "x": 4897.03,
        "y": 4711.67,
        "type": "normal"
      },
      {
        "x": 4805.68,
        "y": 5104.29,
        "type": "normal"
      },
      {
        "x": 4701.97,
        "y": 6289.54,
        "type": "normal"
      },
      {
        "x": 4829.85,
        "y": 6307.42,
        "type": "and"
      },
      {
        "x": 4703.95,
        "y": 6328.64,
        "type": "normal"
      },
      {
        "x": 4960.13,
        "y": 6326.63,
        "type": "normal"
      },
      {
        "x": 4829.86,
        "y": 6376.54,
        "type": "and"
      },
      {
        "x": 4701.03,
        "y": 6396.3,
        "type": "normal"
      },
      {
        "x": 4965.1,
        "y": 6392.54,
        "type": "normal"
      },
      {
        "x": 4705.05,
        "y": 6443.59,
        "type": "normal"
      },
      {
        "x": 4954.84,
        "y": 6470.81,
        "type": "normal"
      },
      {
        "x": 4708.44,
        "y": 6490.55,
        "type": "normal"
      },
      {
        "x": 4701.24,
        "y": 6364.31,
        "type": "normal"
      },
      {
        "x": 4821.32,
        "y": 6446.93,
        "type": "and"
      },
      {
        "x": 2911.86,
        "y": 6573.59,
        "type": "positive"
      },
      {
        "x": 3161.16,
        "y": 6575.85,
        "type": "positive"
      },
      {
        "x": 2910.65,
        "y": 6626.05,
        "type": "positive"
      },
      {
        "x": 3160.26,
        "y": 6630.99,
        "type": "positive"
      },
      {
        "x": 4816.46,
        "y": 6526.75,
        "type": "and"
      },
      {
        "x": 4708.8,
        "y": 6524.46,
        "type": "normal"
      },
      {
        "x": 4707.33,
        "y": 6553.74,
        "type": "normal"
      },
      {
        "x": 4971.23,
        "y": 6549.44,
        "type": "normal"
      },
      {
        "x": 5674.98,
        "y": 5807.03,
        "type": "normal"
      },
      {
        "x": 5674.81,
        "y": 5780.04,
        "type": "normal"
      },
      {
        "x": 5678.6,
        "y": 5832.98,
        "type": "normal"
      },
      {
        "x": 5675.1,
        "y": 5746.23,
        "type": "normal"
      },
      {
        "x": 5671.1,
        "y": 5719.23,
        "type": "normal"
      },
      {
        "x": 2914.71,
        "y": 6730.56,
        "type": "positive"
      },
      {
        "x": 2910.45,
        "y": 6679.95,
        "type": "positive"
      },
      {
        "x": 3159.91,
        "y": 6738.24,
        "type": "positive"
      },
      {
        "x": 3160.32,
        "y": 6684.02,
        "type": "positive"
      },
      {
        "x": 3034.92,
        "y": 6879.27,
        "type": "positive"
      },
      {
        "x": 6013.19,
        "y": 6943.7,
        "type": "normal"
      },
      {
        "x": 6203.92,
        "y": 6361.32,
        "type": "normal"
      },
      {
        "x": 6205.03,
        "y": 6452.62,
        "type": "normal"
      },
      {
        "x": 6203.92,
        "y": 6534.02,
        "type": "normal"
      },
      {
        "x": 6196.69,
        "y": 6120.72,
        "type": "normal"
      },
      {
        "x": 6197.8,
        "y": 6212.02,
        "type": "normal"
      },
      {
        "x": 6196.69,
        "y": 6293.42,
        "type": "normal"
      },
      {
        "x": 6202.99,
        "y": 5874.86,
        "type": "normal"
      },
      {
        "x": 6204.09,
        "y": 5966.16,
        "type": "normal"
      },
      {
        "x": 6202.99,
        "y": 6047.56,
        "type": "normal"
      },
      {
        "x": 6211.47,
        "y": 5618.3,
        "type": "normal"
      },
      {
        "x": 6212.57,
        "y": 5709.6,
        "type": "normal"
      },
      {
        "x": 6201.86,
        "y": 5792.54,
        "type": "normal"
      },
      {
        "x": 6203.4,
        "y": 6638.32,
        "type": "normal"
      },
      {
        "x": 6280.51,
        "y": 6387.72,
        "type": "not"
      },
      {
        "x": 6273.26,
        "y": 6147.12,
        "type": "not"
      },
      {
        "x": 6279.55,
        "y": 5901.26,
        "type": "not"
      },
      {
        "x": 6288.05,
        "y": 5644.7,
        "type": "not"
      },
      {
        "x": 6381.51,
        "y": 6515.72,
        "type": "and"
      },
      {
        "x": 6374.26,
        "y": 6275.12,
        "type": "and"
      },
      {
        "x": 6380.55,
        "y": 6029.26,
        "type": "and"
      },
      {
        "x": 6394.03,
        "y": 5625.7,
        "type": "and"
      },
      {
        "x": 6386.51,
        "y": 6368.72,
        "type": "and"
      },
      {
        "x": 6379.26,
        "y": 6128.12,
        "type": "and"
      },
      {
        "x": 6385.55,
        "y": 5882.26,
        "type": "and"
      },
      {
        "x": 6389.03,
        "y": 5772.7,
        "type": "and"
      },
      {
        "x": 6279.97,
        "y": 6664.72,
        "type": "not"
      },
      {
        "x": 6385.97,
        "y": 6645.72,
        "type": "and"
      },
      {
        "x": 6204.49,
        "y": 6729.62,
        "type": "normal"
      },
      {
        "x": 6380.97,
        "y": 6792.72,
        "type": "and"
      },
      {
        "x": 6203.4,
        "y": 6811.02,
        "type": "normal"
      },
      {
        "x": 6485.51,
        "y": 6441.72,
        "type": "or"
      },
      {
        "x": 6478.26,
        "y": 6201.12,
        "type": "or"
      },
      {
        "x": 6493.03,
        "y": 5698.7,
        "type": "or"
      },
      {
        "x": 6484.55,
        "y": 5955.26,
        "type": "or"
      },
      {
        "x": 6484.97,
        "y": 6718.72,
        "type": "or"
      },
      {
        "x": 6582.78,
        "y": 6217.52,
        "type": "normal"
      },
      {
        "x": 6590.03,
        "y": 6458.12,
        "type": "normal"
      },
      {
        "x": 6589.07,
        "y": 5971.66,
        "type": "normal"
      },
      {
        "x": 6589.49,
        "y": 6735.12,
        "type": "normal"
      },
      {
        "x": 6597.55,
        "y": 5715.1,
        "type": "normal"
      },
      {
        "x": 6686.4,
        "y": 5966.12,
        "type": "negative"
      },
      {
        "x": 6681.22,
        "y": 6209.92,
        "type": "negative"
      },
      {
        "x": 6686.42,
        "y": 6445.95,
        "type": "negative"
      },
      {
        "x": 6684.53,
        "y": 5707.51,
        "type": "negative"
      },
      {
        "x": 6704.57,
        "y": 6726.08,
        "type": "negative"
      }
    ],
    "connections": [
      {
        "from": 105,
        "to": 114,
        "fromPin": "OUT",
        "toPin": "B"
      },
      {
        "from": 101,
        "to": 114,
        "fromPin": "OUT",
        "toPin": "A"
      },
      {
        "from": 97,
        "to": 105,
        "fromPin": "OUT",
        "toPin": "A"
      },
      {
        "from": 84,
        "to": 105,
        "fromPin": "OUT",
        "toPin": "B"
      },
      {
        "from": 85,
        "to": 97,
        "fromPin": "OUT",
        "toPin": "IN"
      },
      {
        "from": 85,
        "to": 101,
        "fromPin": "OUT",
        "toPin": "B"
      },
      {
        "from": 86,
        "to": 101,
        "fromPin": "OUT",
        "toPin": "A"
      },
      {
        "from": 114,
        "to": 120,
        "fromPin": "OUT",
        "toPin": "IN"
      },
      {
        "from": 106,
        "to": 115,
        "fromPin": "OUT",
        "toPin": "B"
      },
      {
        "from": 102,
        "to": 115,
        "fromPin": "OUT",
        "toPin": "A"
      },
      {
        "from": 98,
        "to": 106,
        "fromPin": "OUT",
        "toPin": "A"
      },
      {
        "from": 87,
        "to": 106,
        "fromPin": "OUT",
        "toPin": "B"
      },
      {
        "from": 88,
        "to": 98,
        "fromPin": "OUT",
        "toPin": "IN"
      },
      {
        "from": 88,
        "to": 102,
        "fromPin": "OUT",
        "toPin": "B"
      },
      {
        "from": 89,
        "to": 102,
        "fromPin": "OUT",
        "toPin": "A"
      },
      {
        "from": 115,
        "to": 119,
        "fromPin": "OUT",
        "toPin": "IN"
      },
      {
        "from": 107,
        "to": 117,
        "fromPin": "OUT",
        "toPin": "B"
      },
      {
        "from": 103,
        "to": 117,
        "fromPin": "OUT",
        "toPin": "A"
      },
      {
        "from": 99,
        "to": 107,
        "fromPin": "OUT",
        "toPin": "A"
      },
      {
        "from": 90,
        "to": 107,
        "fromPin": "OUT",
        "toPin": "B"
      },
      {
        "from": 91,
        "to": 99,
        "fromPin": "OUT",
        "toPin": "IN"
      },
      {
        "from": 91,
        "to": 103,
        "fromPin": "OUT",
        "toPin": "B"
      },
      {
        "from": 92,
        "to": 103,
        "fromPin": "OUT",
        "toPin": "A"
      },
      {
        "from": 117,
        "to": 121,
        "fromPin": "OUT",
        "toPin": "IN"
      },
      {
        "from": 82,
        "to": 83,
        "fromPin": "OUT",
        "toPin": "IN"
      },
      {
        "from": 83,
        "to": 91,
        "fromPin": "OUT",
        "toPin": "IN"
      },
      {
        "from": 83,
        "to": 88,
        "fromPin": "OUT",
        "toPin": "IN"
      },
      {
        "from": 83,
        "to": 85,
        "fromPin": "OUT",
        "toPin": "IN"
      },
      {
        "from": 110,
        "to": 118,
        "fromPin": "OUT",
        "toPin": "B"
      },
      {
        "from": 112,
        "to": 118,
        "fromPin": "OUT",
        "toPin": "A"
      },
      {
        "from": 109,
        "to": 110,
        "fromPin": "OUT",
        "toPin": "A"
      },
      {
        "from": 96,
        "to": 110,
        "fromPin": "OUT",
        "toPin": "B"
      },
      {
        "from": 111,
        "to": 109,
        "fromPin": "OUT",
        "toPin": "IN"
      },
      {
        "from": 111,
        "to": 112,
        "fromPin": "OUT",
        "toPin": "B"
      },
      {
        "from": 113,
        "to": 112,
        "fromPin": "OUT",
        "toPin": "A"
      },
      {
        "from": 118,
        "to": 122,
        "fromPin": "OUT",
        "toPin": "IN"
      },
      {
        "from": 83,
        "to": 111,
        "fromPin": "OUT",
        "toPin": "IN"
      },
      {
        "from": 104,
        "to": 116,
        "fromPin": "OUT",
        "toPin": "B"
      },
      {
        "from": 108,
        "to": 116,
        "fromPin": "OUT",
        "toPin": "A"
      },
      {
        "from": 100,
        "to": 104,
        "fromPin": "OUT",
        "toPin": "A"
      },
      {
        "from": 93,
        "to": 104,
        "fromPin": "OUT",
        "toPin": "B"
      },
      {
        "from": 94,
        "to": 100,
        "fromPin": "OUT",
        "toPin": "IN"
      },
      {
        "from": 94,
        "to": 108,
        "fromPin": "OUT",
        "toPin": "B"
      },
      {
        "from": 116,
        "to": 123,
        "fromPin": "OUT",
        "toPin": "IN"
      },
      {
        "from": 75,
        "to": 96,
        "fromPin": "OUT",
        "toPin": "IN"
      },
      {
        "from": 73,
        "to": 84,
        "fromPin": "OUT",
        "toPin": "IN"
      },
      {
        "from": 74,
        "to": 87,
        "fromPin": "OUT",
        "toPin": "IN"
      },
      {
        "from": 83,
        "to": 94,
        "fromPin": "OUT",
        "toPin": "IN"
      },
      {
        "from": 70,
        "to": 69,
        "fromPin": "OUT",
        "toPin": "B"
      },
      {
        "from": 80,
        "to": 70,
        "fromPin": "OUT",
        "toPin": "IN"
      },
      {
        "from": 71,
        "to": 69,
        "fromPin": "OUT",
        "toPin": "A"
      },
      {
        "from": 78,
        "to": 71,
        "fromPin": "OUT",
        "toPin": "IN"
      },
      {
        "from": 58,
        "to": 57,
        "fromPin": "OUT",
        "toPin": "A"
      },
      {
        "from": 53,
        "to": 54,
        "fromPin": "OUT",
        "toPin": "B"
      },
      {
        "from": 55,
        "to": 54,
        "fromPin": "OUT",
        "toPin": "A"
      },
      {
        "from": 81,
        "to": 60,
        "fromPin": "OUT",
        "toPin": "IN"
      },
      {
        "from": 66,
        "to": 53,
        "fromPin": "OUT",
        "toPin": "IN"
      },
      {
        "from": 65,
        "to": 55,
        "fromPin": "OUT",
        "toPin": "IN"
      },
      {
        "from": 67,
        "to": 58,
        "fromPin": "OUT",
        "toPin": "IN"
      },
      {
        "from": 69,
        "to": 72,
        "fromPin": "OUT",
        "toPin": "IN"
      },
      {
        "from": 57,
        "to": 59,
        "fromPin": "OUT",
        "toPin": "IN"
      },
      {
        "from": 54,
        "to": 56,
        "fromPin": "OUT",
        "toPin": "IN"
      },
      {
        "from": 72,
        "to": 113,
        "fromPin": "OUT",
        "toPin": "IN"
      },
      {
        "from": 61,
        "to": 86,
        "fromPin": "OUT",
        "toPin": "IN"
      },
      {
        "from": 59,
        "to": 89,
        "fromPin": "OUT",
        "toPin": "IN"
      },
      {
        "from": 56,
        "to": 92,
        "fromPin": "OUT",
        "toPin": "IN"
      },
      {
        "from": 123,
        "to": 127,
        "fromPin": "OUT",
        "toPin": "IN"
      },
      {
        "from": 121,
        "to": 124,
        "fromPin": "OUT",
        "toPin": "IN"
      },
      {
        "from": 119,
        "to": 125,
        "fromPin": "OUT",
        "toPin": "IN"
      },
      {
        "from": 120,
        "to": 126,
        "fromPin": "OUT",
        "toPin": "IN"
      },
      {
        "from": 122,
        "to": 128,
        "fromPin": "OUT",
        "toPin": "IN"
      },
      {
        "from": 1,
        "to": 11,
        "fromPin": "OUT",
        "toPin": "A"
      },
      {
        "from": 0,
        "to": 11,
        "fromPin": "OUT",
        "toPin": "B"
      },
      {
        "from": 1,
        "to": 12,
        "fromPin": "OUT",
        "toPin": "A"
      },
      {
        "from": 0,
        "to": 12,
        "fromPin": "OUT",
        "toPin": "B"
      },
      {
        "from": 14,
        "to": 31,
        "fromPin": "OUT",
        "toPin": "A"
      },
      {
        "from": 13,
        "to": 31,
        "fromPin": "OUT",
        "toPin": "B"
      },
      {
        "from": 14,
        "to": 32,
        "fromPin": "OUT",
        "toPin": "A"
      },
      {
        "from": 13,
        "to": 32,
        "fromPin": "OUT",
        "toPin": "B"
      },
      {
        "from": 12,
        "to": 13,
        "fromPin": "OUT",
        "toPin": "IN"
      },
      {
        "from": 11,
        "to": 36,
        "fromPin": "OUT",
        "toPin": "B"
      },
      {
        "from": 31,
        "to": 36,
        "fromPin": "OUT",
        "toPin": "A"
      },
      {
        "from": 3,
        "to": 17,
        "fromPin": "OUT",
        "toPin": "A"
      },
      {
        "from": 2,
        "to": 17,
        "fromPin": "OUT",
        "toPin": "B"
      },
      {
        "from": 3,
        "to": 15,
        "fromPin": "OUT",
        "toPin": "A"
      },
      {
        "from": 2,
        "to": 15,
        "fromPin": "OUT",
        "toPin": "B"
      },
      {
        "from": 16,
        "to": 34,
        "fromPin": "OUT",
        "toPin": "B"
      },
      {
        "from": 16,
        "to": 33,
        "fromPin": "OUT",
        "toPin": "B"
      },
      {
        "from": 15,
        "to": 16,
        "fromPin": "OUT",
        "toPin": "IN"
      },
      {
        "from": 17,
        "to": 37,
        "fromPin": "OUT",
        "toPin": "B"
      },
      {
        "from": 34,
        "to": 37,
        "fromPin": "OUT",
        "toPin": "A"
      },
      {
        "from": 33,
        "to": 45,
        "fromPin": "OUT",
        "toPin": "IN"
      },
      {
        "from": 36,
        "to": 47,
        "fromPin": "OUT",
        "toPin": "IN"
      },
      {
        "from": 18,
        "to": 34,
        "fromPin": "OUT",
        "toPin": "A"
      },
      {
        "from": 18,
        "to": 33,
        "fromPin": "OUT",
        "toPin": "A"
      },
      {
        "from": 5,
        "to": 21,
        "fromPin": "OUT",
        "toPin": "A"
      },
      {
        "from": 4,
        "to": 21,
        "fromPin": "OUT",
        "toPin": "B"
      },
      {
        "from": 5,
        "to": 19,
        "fromPin": "OUT",
        "toPin": "A"
      },
      {
        "from": 4,
        "to": 19,
        "fromPin": "OUT",
        "toPin": "B"
      },
      {
        "from": 22,
        "to": 39,
        "fromPin": "OUT",
        "toPin": "A"
      },
      {
        "from": 20,
        "to": 39,
        "fromPin": "OUT",
        "toPin": "B"
      },
      {
        "from": 22,
        "to": 35,
        "fromPin": "OUT",
        "toPin": "A"
      },
      {
        "from": 20,
        "to": 35,
        "fromPin": "OUT",
        "toPin": "B"
      },
      {
        "from": 19,
        "to": 20,
        "fromPin": "OUT",
        "toPin": "IN"
      },
      {
        "from": 21,
        "to": 38,
        "fromPin": "OUT",
        "toPin": "B"
      },
      {
        "from": 39,
        "to": 38,
        "fromPin": "OUT",
        "toPin": "A"
      },
      {
        "from": 35,
        "to": 46,
        "fromPin": "OUT",
        "toPin": "IN"
      },
      {
        "from": 8,
        "to": 25,
        "fromPin": "OUT",
        "toPin": "B"
      },
      {
        "from": 8,
        "to": 23,
        "fromPin": "OUT",
        "toPin": "B"
      },
      {
        "from": 44,
        "to": 43,
        "fromPin": "OUT",
        "toPin": "A"
      },
      {
        "from": 24,
        "to": 43,
        "fromPin": "OUT",
        "toPin": "B"
      },
      {
        "from": 44,
        "to": 41,
        "fromPin": "OUT",
        "toPin": "A"
      },
      {
        "from": 24,
        "to": 41,
        "fromPin": "OUT",
        "toPin": "B"
      },
      {
        "from": 23,
        "to": 24,
        "fromPin": "OUT",
        "toPin": "IN"
      },
      {
        "from": 25,
        "to": 42,
        "fromPin": "OUT",
        "toPin": "B"
      },
      {
        "from": 43,
        "to": 42,
        "fromPin": "OUT",
        "toPin": "A"
      },
      {
        "from": 38,
        "to": 48,
        "fromPin": "OUT",
        "toPin": "IN"
      },
      {
        "from": 41,
        "to": 49,
        "fromPin": "OUT",
        "toPin": "IN"
      },
      {
        "from": 49,
        "to": 75,
        "fromPin": "OUT",
        "toPin": "IN"
      },
      {
        "from": 46,
        "to": 73,
        "fromPin": "OUT",
        "toPin": "IN"
      },
      {
        "from": 45,
        "to": 74,
        "fromPin": "OUT",
        "toPin": "IN"
      },
      {
        "from": 28,
        "to": 25,
        "fromPin": "OUT",
        "toPin": "A"
      },
      {
        "from": 28,
        "to": 23,
        "fromPin": "OUT",
        "toPin": "A"
      },
      {
        "from": 42,
        "to": 50,
        "fromPin": "OUT",
        "toPin": "IN"
      },
      {
        "from": 50,
        "to": 22,
        "fromPin": "OUT",
        "toPin": "IN"
      },
      {
        "from": 30,
        "to": 28,
        "fromPin": "OUT",
        "toPin": "IN"
      },
      {
        "from": 9,
        "to": 8,
        "fromPin": "OUT",
        "toPin": "IN"
      },
      {
        "from": 48,
        "to": 18,
        "fromPin": "OUT",
        "toPin": "IN"
      },
      {
        "from": 32,
        "to": 51,
        "fromPin": "OUT",
        "toPin": "IN"
      },
      {
        "from": 29,
        "to": 5,
        "fromPin": "OUT",
        "toPin": "IN"
      },
      {
        "from": 10,
        "to": 4,
        "fromPin": "OUT",
        "toPin": "IN"
      },
      {
        "from": 6,
        "to": 2,
        "fromPin": "OUT",
        "toPin": "IN"
      },
      {
        "from": 26,
        "to": 3,
        "fromPin": "OUT",
        "toPin": "IN"
      },
      {
        "from": 27,
        "to": 1,
        "fromPin": "OUT",
        "toPin": "IN"
      },
      {
        "from": 7,
        "to": 0,
        "fromPin": "OUT",
        "toPin": "IN"
      },
      {
        "from": 65,
        "to": 7,
        "fromPin": "OUT",
        "toPin": "IN"
      },
      {
        "from": 67,
        "to": 6,
        "fromPin": "OUT",
        "toPin": "IN"
      },
      {
        "from": 79,
        "to": 10,
        "fromPin": "OUT",
        "toPin": "IN"
      },
      {
        "from": 78,
        "to": 9,
        "fromPin": "OUT",
        "toPin": "IN"
      },
      {
        "from": 66,
        "to": 27,
        "fromPin": "OUT",
        "toPin": "IN"
      },
      {
        "from": 68,
        "to": 26,
        "fromPin": "OUT",
        "toPin": "IN"
      },
      {
        "from": 81,
        "to": 29,
        "fromPin": "OUT",
        "toPin": "IN"
      },
      {
        "from": 80,
        "to": 30,
        "fromPin": "OUT",
        "toPin": "IN"
      },
      {
        "from": 47,
        "to": 77,
        "fromPin": "OUT",
        "toPin": "IN"
      },
      {
        "from": 51,
        "to": 76,
        "fromPin": "OUT",
        "toPin": "IN"
      },
      {
        "from": 77,
        "to": 93,
        "fromPin": "OUT",
        "toPin": "IN"
      },
      {
        "from": 95,
        "to": 108,
        "fromPin": "OUT",
        "toPin": "A"
      },
      {
        "from": 76,
        "to": 90,
        "fromPin": "OUT",
        "toPin": "IN"
      },
      {
        "from": 37,
        "to": 52,
        "fromPin": "OUT",
        "toPin": "IN"
      },
      {
        "from": 52,
        "to": 14,
        "fromPin": "OUT",
        "toPin": "IN"
      },
      {
        "from": 64,
        "to": 61,
        "fromPin": "OUT",
        "toPin": "IN"
      },
      {
        "from": 60,
        "to": 64,
        "fromPin": "OUT",
        "toPin": "B"
      },
      {
        "from": 62,
        "to": 64,
        "fromPin": "OUT",
        "toPin": "A"
      },
      {
        "from": 63,
        "to": 57,
        "fromPin": "OUT",
        "toPin": "B"
      },
      {
        "from": 68,
        "to": 63,
        "fromPin": "OUT",
        "toPin": "IN"
      },
      {
        "from": 79,
        "to": 62,
        "fromPin": "OUT",
        "toPin": "IN"
      }
    ],
    "timestamp": 1765761944316
  }
]